[
  {
    "username": "Campanilla",
    "password": "pass123123",
    "img": "https://i.imgur.com/vWOnCRm.jpg",
    "age": "2",
    "gender": "1"
  },
  {
    "username": "Talula",
    "password": "pass123123",
    "img": "https://i.imgur.com/tYSaS46.jpg",
    "age": "6",
    "gender": "1"
  },
  {
    "username": "Sofifú",
    "password": "pass123123",
    "img": "https://i.imgur.com/0NS8OWu.jpg",
    "age": "6",
    "gender": "1"
  },
  {
    "username": "Roquefort",
    "password": "pass123123",
    "img": "https://i.imgur.com/hvG2OF6.jpg",
    "age": "5",
    "gender": "0"
  },
  {
    "username": "Coco",
    "password": "pass123123",
    "img": "https://i.imgur.com/uUl8EOd.jpg",
    "age": "1",
    "gender": "0"
  },
  {
    "username": "Nori",
    "password": "pass123123",
    "img": "https://i.imgur.com/CfJsm1G.jpg",
    "age": "1",
    "gender": "1"
  },
  {
    "username": "Huevo",
    "password": "pass123123",
    "img": "https://pixel.nymag.com/imgs/daily/vulture/2019/03/13/13-captain-marvel-flerken-cat.w700.h700.jpg",
    "age": "10",
    "gender": "0"
  }
]
